<?xml version="1.0" ?>
<Presentation>
  <div class="page">
    <p>Scott Wen-tau Yih</p>
  </div>
  <div class="page"/>
  <div class="page"/>
  <div class="page">
    <p>Knowledge</p>
    <p>Base .sister_of(justin_bieber, )</p>
    <p>Who is Justin Biebers sister?</p>
    <p>.sibling_of(justin_bieber, x)  gender(x, female)</p>
    <p>semantic parsing</p>
    <p>query matching</p>
    <p>Jazmyn Bieber</p>
  </div>
  <div class="page">
    <p>Knowledge</p>
    <p>Base</p>
    <p>Who is Justin Biebers sister?</p>
    <p>.sibling_of(justin_bieber, x)  gender(x, female)</p>
    <p>semantic parsing query</p>
    <p>Jazmyn Bieber</p>
  </div>
  <div class="page">
    <p>What was the date that Minnesota became a state?</p>
    <p>When was the state Minnesota created?</p>
    <p>Minnesota's date it entered the union?</p>
    <p>location.dated_location.date_founded</p>
  </div>
  <div class="page">
    <p>directly</p>
    <p>grows staged</p>
    <p>Basic idea</p>
  </div>
  <div class="page">
    <p>Addresses Key Challenges</p>
  </div>
  <div class="page">
    <p>Introduction</p>
    <p>Background  Graph knowledge base</p>
    <p>Query graph</p>
  </div>
  <div class="page">
    <p>Family Guy cvt2</p>
    <p>Meg Grif fin</p>
    <p>Lacey Chabert</p>
    <p>cvt1</p>
    <p>fr o</p>
    <p>m</p>
    <p>cvt3</p>
    <p>series</p>
    <p>Mil a Kunis</p>
  </div>
  <div class="page">
    <p>Family Guy cast</p>
    <p>Meg Grif finargmin</p>
    <p>xy</p>
    <p>topic entity core inferential chain</p>
    <p>constraints</p>
  </div>
  <div class="page">
    <p>Introduction</p>
    <p>Background</p>
    <p>Staged Query Graph Generation (Our Approach)  Link topic entity</p>
    <p>Identify core inferential chain</p>
    <p>Augment constraints</p>
  </div>
  <div class="page">
    <p>Staged</p>
    <p>Meg Family Guy</p>
    <p>Family Guy s1</p>
    <p>Meg Grif fin s2</p>
    <p>s0</p>
    <p>(1) Link Topic Entity</p>
  </div>
  <div class="page">
    <p>Staged</p>
    <p>Meg Family Guy</p>
    <p>(2) Identify Core Inferential Chain</p>
    <p>Family Guy s1</p>
    <p>Family Guy cast actor xy s3</p>
    <p>Family Guy writer start xy s4</p>
    <p>Family Guy genre x s5</p>
  </div>
  <div class="page">
    <p>Staged</p>
    <p>Meg Family Guy</p>
    <p>(3) Augment Constraints</p>
    <p>Family Guy cast actor xy</p>
    <p>Family Guy cast actor xy</p>
    <p>Meg Grif fin</p>
    <p>Family Guy xy</p>
    <p>Meg Grif finargmin</p>
    <p>s3</p>
    <p>s6</p>
    <p>s7</p>
  </div>
  <div class="page">
    <p>Family Guy s1</p>
    <p>Meg Grif fin s2</p>
    <p>s0</p>
  </div>
  <div class="page">
    <p>Family Guy s1</p>
    <p>Family Guy cast actor xy s3</p>
    <p>Family Guy writer start xy s4</p>
    <p>Family Guy genre x s5</p>
    <p>Who first voiced Meg on Family Guy?</p>
    <p>{castactor, writerstart, genre}</p>
  </div>
  <div class="page">
    <p>Input is mapped to two -dimensional vectors</p>
    <p>= exp cos(,)</p>
    <p>exp cos(,)</p>
    <p>R    R</p>
    <p>who voiced meg on  castactor</p>
    <p>max max</p>
    <p>...</p>
    <p>...</p>
    <p>... max</p>
    <p>...</p>
    <p>...</p>
    <p>&lt;s&gt; w1 w2 wT &lt;/s&gt;</p>
    <p>... ...</p>
  </div>
  <div class="page">
    <p>Who voiced Family Guy</p>
    <p>cast FamilyGuy  actor</p>
    <p>One or more constraint nodes can be added to  or    : Additional property of this event (e.g., character  MegGriffin )</p>
    <p>: Additional property of the answer entity (e.g., gender)</p>
    <p>Family Guy cast actor xy</p>
    <p>Family Guy cast actor xy</p>
    <p>Meg Grif fin</p>
    <p>Family Guy xy</p>
    <p>Meg Grif finargmin</p>
    <p>s3</p>
    <p>s6</p>
    <p>s7</p>
    <p>Family Guy cast actor xy s3</p>
  </div>
  <div class="page">
    <p>Who first voiced Meg on Family Guy?</p>
    <p>Family Guy cast actor xy s3</p>
    <p>Family Guy writer start xy s4</p>
  </div>
  <div class="page">
    <p>Who first voiced Meg on Family Guy?</p>
    <p>Family Guy cast actor xy s3</p>
    <p>Family Guy xy</p>
    <p>Meg Grif finargmin s7</p>
  </div>
  <div class="page">
    <p>=Who first voiced Meg on Family Guy?</p>
    <p>Family Guy cast</p>
    <p>Meg Grif finargmin</p>
    <p>xy</p>
    <p>=</p>
  </div>
  <div class="page">
    <p>Introduction</p>
    <p>Background</p>
    <p>Staged Query Graph Generation (Our Approach)</p>
    <p>Experiments  Data &amp; evaluation metric</p>
    <p>Creating training data from Q/A pairs</p>
    <p>Results</p>
  </div>
  <div class="page">
    <p>What character did Natalie Portman play in Star Wars? Padme Amidala</p>
    <p>What currency do you use in Costa Rica? Costa Rican colon</p>
    <p>What did Obama study in school? political science</p>
    <p>What do Michelle Obama do for a living? writer, lawyer</p>
    <p>What killed Sammy Davis Jr? throat cancer [Examples from Berant]</p>
  </div>
  <div class="page">
    <p>Relation Matching (Identifying Core Inferential Chain)</p>
    <p>Pattern Inferential Chain</p>
    <p>what was &lt;e&gt; known for people.person.profession</p>
    <p>what kind of government does &lt;e&gt; have location.country.form_of_government</p>
    <p>what year were the &lt;e&gt; established sports.sports_team.founded</p>
    <p>what city was &lt;e&gt; born in people.person.place_of_birth</p>
    <p>what did &lt;e&gt; die from people.deceased_person.cause_of_death</p>
    <p>who married &lt;e&gt; people.person.spouse_s</p>
    <p>people.marriage.spouse</p>
  </div>
  <div class="page">
    <p>Reward Function</p>
  </div>
  <div class="page">
    <p>Avg. F1 (Accuracy) on WebQuestions Test Set</p>
    <p>Yao-14 Berant-13 Bao-14 Bordes-14b Berant-14 Yang-14 Yao-15 Wang-14 Yih-15</p>
  </div>
  <div class="page">
    <p>Method #Entities Covered Ques. Labeled Ent.</p>
    <p>Freebase API 19,485 98.8% 81.2%</p>
    <p>Yang &amp; Chang, ACL-15 9,147 99.8% 87.8%</p>
  </div>
  <div class="page"/>
  <div class="page">
    <p>A random sample of 100 incorrectly answered questions</p>
  </div>
  <div class="page">
    <p>directly</p>
  </div>
  <div class="page">
    <p>http://aka.ms/sent2vec</p>
    <p>http://aka.ms/codalab-webq</p>
    <p>http://aka.ms/stagg</p>
  </div>
</Presentation>
