<?xml version="1.0" ?>
<Presentation>
  <div class="page">
    <p>Automatic Web Tagging and Person Tagging</p>
    <p>Using Language Models</p>
    <p>- Qiaozhu Mei, Yi Zhang</p>
    <p>Presented by Jessica Gronski</p>
    <p>University of Illinois at Urbana-Champaign</p>
    <p>University of California at Santa Cruz</p>
  </div>
  <div class="page">
    <p>Tagging a Web Document</p>
    <p>The dual problem of search/retrieval: [Mei et al. 2007]</p>
    <p>Retrieval: short description (query)  relevant documents</p>
    <p>Tagging: document  short description (tag)  To summarize the content of documents</p>
    <p>To access the document in the future</p>
    <p>Text Document</p>
    <p>Query/Tag</p>
    <p>retrieval</p>
    <p>tagging</p>
  </div>
  <div class="page">
    <p>Social Bookmarking of Web Documents</p>
    <p>Web documents Social bookmarks (tags)</p>
  </div>
  <div class="page">
    <p>Existing Work on Social Bookmarking</p>
    <p>Social Bookmarking Systems  Del.icio.us, Digg, Citeulike, etc.</p>
    <p>Enhance Social bookmarking systems  Anti-spam [Koutrika et al 2007]  Search&amp; ranking tags [Hotho et al 2006]</p>
    <p>Utilize social bookmarks  Visualization [Dubinko et al. 2006]  Summarization [Boydell et al. 2007]  Use tags to help web search:</p>
    <p>[Heymann et al. 2008]; [Zhou et al. 2008]</p>
  </div>
  <div class="page">
    <p>Research Questions</p>
    <p>Can we automatically generate tags for web documents?  Meaningful, compact, relevant</p>
    <p>Can we generate tags for other web objects, such as web users?</p>
  </div>
  <div class="page">
    <p>Applications of Automatic Tagging</p>
    <p>Summarizing documents/ web objects</p>
    <p>Suggest social bookmarks</p>
    <p>Refine queries for web search  Finding good queries to a document</p>
    <p>Suggest good keywords for online advertising</p>
  </div>
  <div class="page">
    <p>Rest of the Talk</p>
    <p>A probabilistic approach to tag generation  Candidate Tag Selection</p>
    <p>Web document representation</p>
    <p>Tag ranking</p>
    <p>Experiments  Web documents tagging;</p>
    <p>web user tagging</p>
    <p>Summary</p>
  </div>
  <div class="page">
    <p>Our Method</p>
    <p>data 0.1599 statistics 0.0752 tutorial 0.0660 analysis 0.0372 software 0.0311 model 0.0310 frequent 0.0233 probabilistic 0.0188 algorithm 0.0173</p>
    <p>ipod nano, data mining, presidential campaign index structure, statistics tutorial, computer science</p>
    <p>Candidate tag pool</p>
    <p>data mining 0.26 statistics tutorial 0.19 computer science 0.17 index structure 0.01  ipod nano 0.00001 presidential campaign 0.0</p>
    <p>Ranking candidate tags</p>
    <p>User-Generated Corpus (e.g., Del.icio.us, Wikipedia)</p>
    <p>Web Documents Multinomial word Distribution</p>
    <p>representation</p>
  </div>
  <div class="page">
    <p>Candidate Tag Selection</p>
    <p>Meaningful, compact, user-oriented</p>
    <p>From social bookmarking data  E.g., Del.icio.us</p>
    <p>Single tags  tags that other people used  phrases  statistically significant bigrams</p>
    <p>From other user-generated web contents  E.g., Wikipedia</p>
    <p>Titles of entries in wikipedia</p>
  </div>
  <div class="page">
    <p>Representation of Web Documents</p>
    <p>Multinomial distribution of words</p>
    <p>(unigram language models)  Commonly used in retrieval and</p>
    <p>text mining</p>
    <p>Can be estimated from the content of the document, or from social bookmarks (our approach)  What other people used to tag that</p>
    <p>document</p>
    <p>text 0.16 mining 0.08 data 0.07 probabilistic 0.04 independence 0.03 model 0.03</p>
    <p>Baseline: Use the top words in that distribution to tag a document</p>
  </div>
  <div class="page">
    <p>Tag Ranking: A Probabilistic Approach</p>
    <p>Web documents d  a language model</p>
    <p>A candidate tag t  a language model from its co-occurring tags</p>
    <p>Score and rank t by KL-divergence of these two language models</p>
    <p>w dwp</p>
    <p>twp dwptdDdtf</p>
    <p>)|(</p>
    <p>)|( log)|()||(),(</p>
    <p>),|( Ctwp</p>
    <p>Social Bookmark Collection</p>
  </div>
  <div class="page">
    <p>Rewriting and Efficient Computation</p>
    <p>),()||( )|()|(</p>
    <p>)|,( log)|(</p>
    <p>)|(</p>
    <p>),|( log)|(</p>
    <p>)|(</p>
    <p>)|( log)|(</p>
    <p>)|(</p>
    <p>),|( log)|(</p>
    <p>)|(</p>
    <p>)|( log)|(),(</p>
    <p>CtBiasCdD CtpCwp</p>
    <p>Ctwp dwp</p>
    <p>twp</p>
    <p>Ctwp dwp</p>
    <p>Cwp</p>
    <p>dwp dwp</p>
    <p>Cwp</p>
    <p>Ctwp dwp</p>
    <p>dwp</p>
    <p>twp dwpdtf</p>
    <p>w</p>
    <p>www</p>
    <p>w</p>
    <p>)|,( CwtPMI Bias of using C to represent candidate tag t</p>
    <p>Bias of using C to represent document d (e.g., del.icio.us)</p>
    <p>)]|,([),( CtwPMIEdtf d rank</p>
  </div>
  <div class="page">
    <p>Tagging Web Users</p>
    <p>Summarize the interests and bias of a user</p>
    <p>Web user  a pseudo document</p>
    <p>Estimate a language model from all tags that he used</p>
    <p>The rest is similar to web document tagging</p>
  </div>
  <div class="page">
    <p>Experiments</p>
    <p>Dataset:  Two-week tagging records from Del.icio.us</p>
    <p>Candidate tags:  Top 15,000 Significant 2-grams from del.icio.us;</p>
    <p>titles of all wikipedia entries (5,836,166 entries, around 48,000 appeared in del.icio.us)</p>
    <p>Time Span Bookmarks Distinct Tags</p>
    <p>Distinct Users</p>
  </div>
  <div class="page">
    <p>Tagging Web Documents</p>
    <p>Urls LM p(w|d) Tag = Word Tag = bigram Tag = wikipedia title</p>
    <p>http://kuler.adobe.com/ (158 bookmarks)</p>
    <p>color design webdesign tools adobe graphics flash</p>
    <p>color colour palette colorscheme colours picker cor</p>
    <p>adobe color color design color colour color colors colour design inspiration palette webdesign color</p>
    <p>color colour palette web color colours cor rgb</p>
    <p>http://www.youtube.co m/watch?v=6gmP4nk0EOE (157 bookmarks)</p>
    <p>web2.0 video youtube web internet xml community</p>
    <p>youtube revver vodcast primer comunidad participation ethnograpy</p>
    <p>xml youtube web2.0 youtube video web2.0 web2.0 xml online presentation social video youtube video</p>
    <p>internet video youtube revver research video vodcast primer p2p TV</p>
    <p>Too general, sometimes not</p>
    <p>relevant</p>
    <p>Relevant, precise Meaningful,</p>
    <p>relevant</p>
    <p>overfit data, not real phrases</p>
    <p>Meaningful, relevant</p>
    <p>Meaningful, relevant, real</p>
    <p>But partially covers good</p>
    <p>tags</p>
    <p>But sometimes not meaningful</p>
    <p>overfit data, not real phrases</p>
  </div>
  <div class="page">
    <p>Tagging Web Documents (Cont.)</p>
    <p>Urls LM p(w|d) Tag = Word Tag = bigram Tag = wikipedia title</p>
    <p>http://pipes.yahoo.com (386 bookmarks)</p>
    <p>yahoo rss web2.0 mashup feeds programming pipes</p>
    <p>pipes feeds yahoo mashup rss syndication mashups</p>
    <p>feeds mashups mashup pipes web2.0 yahoo rss web2.0 mashup rss api feeds pipes programming</p>
    <p>pipes yahoo mashups rss syndication mashups blog feeds</p>
    <p>http://www.miniajax.com/ (349 bookmarks)</p>
    <p>ajax javascript web2.0 webdesign programming code webdev</p>
    <p>ajax dhtml javascript moo.fx dragdrop phototype autosuggest</p>
    <p>ajax code code javascript javascript ajax javascript web2.0 css ajax javascript programming</p>
    <p>ajax dhtml javascript moo.fx javascript library javascript -framework</p>
    <p>Too general, sometimes not</p>
    <p>relevant</p>
    <p>Relevant, precise</p>
    <p>But sometimes not meaningful</p>
    <p>Meaningful, relevant</p>
    <p>overfit data, not real phrases</p>
    <p>Meaningful, relevant, real</p>
  </div>
  <div class="page">
    <p>Tagging Web Users</p>
    <p>Users LM p(w|d) Tag = bigram Tag = wikipedia title</p>
    <p>User 1 photography art portraits tools web design geek</p>
    <p>art photography photography portraits digital flickr photoblog photography art photo flickr photography weblog wordpress</p>
    <p>art photography photoblog portraits photography landscapes flickr art contest</p>
    <p>User 2 humor programming photography blog webdesign security funny</p>
    <p>geek hack humor programming hack hacking networking programming geek html geek hacking reference security</p>
    <p>network programming tweak hacking security geek humor sysadmin digitalcamera</p>
    <p>Partially covers the interest</p>
    <p>Meaningful, relevant, real</p>
    <p>overfit data, not real phrases</p>
  </div>
  <div class="page">
    <p>Tagging Web Users (Cont.)</p>
    <p>Users LM p(w|d) Tag = bigram Tag = wikipedia title</p>
    <p>User 3 games arg tools programming sudoku cryptography software</p>
    <p>arg games games puzzles games internet arg code games sudoku code generator community games</p>
    <p>arg games research games puzzles storytelling code generator community games</p>
    <p>User 4 web reference css development rubyonrails tools design</p>
    <p>rubyonrails web css development brower development development editor development forum development firefox javascript tools</p>
    <p>javascript css webdev xhtml dhtml css3 dom</p>
    <p>Missed many good tags</p>
  </div>
  <div class="page">
    <p>Discussions</p>
    <p>Using top tags: too general, sometimes not relevant</p>
    <p>Ranking tags by labeling language models:  Candidate = Social bookmarking words</p>
    <p>Pros: relevant, compact</p>
    <p>Cons: ambiguous, not so meaningful</p>
    <p>Candidate = Social bookmarking bigrams  Pros: more meaningful, relevant</p>
    <p>Cons: overfiting the data, sometimes not real phrases</p>
    <p>Candidate = Wikipedia Titles:  Pros: meaningful, relevant real phrases</p>
    <p>Cons: biased, missed potential good tags. (Bias(t, C))</p>
  </div>
  <div class="page">
    <p>Summary</p>
    <p>Automatic tagging of web documents and web users</p>
    <p>A probabilistic approach based on labeling language models</p>
    <p>Effective when the candidate tags are of high quality</p>
    <p>Future work:  A robust way of generating candidate tags</p>
    <p>Large scale evaluation</p>
  </div>
  <div class="page">
    <p>Thanks!</p>
  </div>
</Presentation>
